{
  "arxiv_id": "2110.13900v5",
  "title_zh": "WavLM：面向全栈语音处理的大规模自监督预训练",
  "one_sentence_summary": "提出WavLM模型，通过联合掩码语音预测与去噪预训练实现全栈语音任务的通用表征学习。",
  "key_contributions": [
    "贡献1：提出将掩码语音预测与语音去噪联合训练的预训练框架，使模型同时具备内容建模和非ASR任务能力",
    "贡献2：引入门控相对位置偏置（gated relative position bias）改进Transformer结构，更好捕获语音序列的顺序信息",
    "贡献3：将训练数据从60k小时扩展至94k小时，在SUPERB基准上取得全面最优性能，覆盖语音识别、说话人验证、语音分离等多种任务"
  ],
  "technical_approach": "WavLM基于HuBERT框架，采用Transformer编码器架构。核心创新包括：（1）预训练阶段同时进行掩码语音预测和语音去噪任务，通过在输入中混入重叠语音或噪声，让模型在预测被掩码部分的同时学习去噪能力，从而提升对说话人身份、语音分离等非ASR任务的表征能力；（2）在Transformer自注意力中引入门控相对位置偏置，通过可学习的门控机制控制不同层对位置信息的利用程度，增强序列建模能力；（3）将预训练数据扩展至94k小时（包含LibriLight 60k、GigaSpeech 10k、VoxPopuli 24k），并提供Base和Large两种规模模型。",
  "datasets_and_benchmarks": [
    "SUPERB benchmark",
    "LibriLight",
    "GigaSpeech",
    "VoxPopuli",
    "LibriSpeech",
    "VoxCeleb1",
    "IEMOCAP",
    "WSJ0-2mix",
    "MOSEI",
    "DNS Challenge"
  ],
  "key_results": "WavLM Large在SUPERB基准13项任务中取得全面最优，在语音识别（ASR）、说话人验证（SV）、语音分离（SS）、说话人日志（SD）等代表性任务上均显著超越HuBERT和wav2vec 2.0等前沿模型。特别在说话人验证和语音分离等非ASR任务上提升显著。",
  "limitations": "模型规模大、预训练计算成本高；去噪预训练策略的噪声类型有限，泛化性有待验证。",
  "connections_to_vla": "WavLM作为强大的语音通用表征模型，可为VLA系统中的语音指令理解、说话人识别、环境声音感知等模块提供高质量特征输入。其多任务通用表征思想与VLA追求的多模态统一表征理念相通，可作为具身智能系统中语音感知的基础编码器。",
  "survey_theme": "音频自监督基础模型",
  "importance_score": 5,
  "keywords": [
    "自监督学习",
    "语音预训练",
    "WavLM",
    "掩码语音预测",
    "语音去噪",
    "SUPERB"
  ]
}