{
  "arxiv_id": "2210.13438v1",
  "title_zh": "高保真神经音频压缩",
  "one_sentence_summary": "提出基于神经网络的实时高保真音频编解码器EnCodec。",
  "key_contributions": [
    "贡献1：提出了一种端到端训练的流式编码器-解码器架构（EnCodec），结合量化潜空间实现实时高保真音频压缩",
    "贡献2：引入单一多尺度频谱对抗器简化训练，并提出新颖的损失平衡机制（loss balancer）稳定训练过程，将损失权重解耦为梯度占比",
    "贡献3：利用轻量级Transformer模型对量化表示进行熵编码，进一步压缩表示达40%，同时保持快于实时的速度"
  ],
  "technical_approach": "EnCodec采用流式编码器-解码器架构，编码器将音频映射到低维潜空间，通过残差向量量化（RVQ）进行离散化，解码器重建音频信号。训练采用重建损失、感知损失和对抗损失的组合，其中对抗损失使用单一多尺度频谱判别器有效减少伪影。创新性地提出损失平衡器，使每个损失的权重定义其在总梯度中的比例，解耦超参数选择与损失尺度的关系。此外引入小型Transformer语言模型对RVQ码本进行熵编码，利用码本间的依赖关系进一步压缩比特率。支持24kHz单声道和48kHz立体声音频。",
  "datasets_and_benchmarks": [
    "DNS Challenge数据集（语音+噪声）",
    "Common Voice数据集",
    "Jamendo音乐数据集",
    "MUSHRA主观评测"
  ],
  "key_results": "在语音、含噪混响语音和音乐等多个音频域的MUSHRA主观测试中，EnCodec在所有评估带宽设置下均优于基线方法（包括Opus、EVS、Lyra v2等），支持1.5-24 kbps的多种码率，48kHz立体声同样表现优异。",
  "limitations": "主观评测成本高、规模有限；极低码率下仍有质量损失；未充分探索更多音频类型的泛化性。",
  "connections_to_vla": "EnCodec作为音频离散化tokenizer，为后续AudioLM、MusicGen等音频语言模型提供了关键的音频token表示，是多模态大语言模型处理音频模态的重要基础组件，可为具身智能中的音频感知和语音交互提供高效压缩表示。",
  "survey_theme": "音频生成与合成",
  "importance_score": 5,
  "keywords": [
    "神经音频编解码",
    "残差向量量化",
    "对抗训练",
    "音频压缩",
    "EnCodec"
  ]
}