{
  "arxiv_id": "2603.12260v1",
  "title_zh": "HumDex：让人形机器人灵巧操作变得简单",
  "one_sentence_summary": "提出便携式遥操作系统HumDex及两阶段模仿学习框架，实现人形机器人全身灵巧操作。",
  "key_contributions": [
    "贡献1：提出HumDex便携式遥操作系统，利用IMU运动追踪解决便携性与精度的权衡问题，实现全身精确追踪",
    "贡献2：引入基于学习的灵巧手重定向方法，无需手动调参即可生成平滑自然的手部运动",
    "贡献3：提出两阶段模仿学习框架，先在多样化人体运动数据上预训练学习通用先验，再在机器人数据上微调以弥合具身差距，大幅提升泛化能力"
  ],
  "technical_approach": "HumDex系统包含三个核心组件：（1）基于IMU的全身运动追踪，兼顾便携性和精度，避免了视觉遥操作中的遮挡问题；（2）基于学习的灵巧手重定向方法，将人手动作映射到机器人灵巧手，生成平滑自然的控制指令，无需繁琐的手动参数调整；（3）两阶段模仿学习框架——第一阶段利用HumDex高效采集的大量人体运动数据进行预训练，学习可泛化的运动先验；第二阶段在少量机器人实际操作数据上微调，弥合人与机器人之间的具身差距。该方法以较低的数据采集成本实现了对新配置、新物体和新背景的良好泛化。整个系统完全开源可复现。",
  "datasets_and_benchmarks": [
    "自采集的人体运动数据集",
    "自采集的机器人操作演示数据集"
  ],
  "key_results": "通过两阶段模仿学习框架，HumDex在人形机器人全身灵巧操作任务上显著提升了泛化能力，能够在最小数据采集成本下泛化至新的物体配置、新物体和新背景。系统完全开源，具备较高的可复现性和实用价值。",
  "limitations": "依赖IMU传感器可能存在累积漂移问题；两阶段训练策略在更复杂长序列任务上的泛化效果有待验证。",
  "connections_to_vla": "HumDex为VLA模型提供了高效的全身灵巧操作数据采集方案，其预训练-微调范式与VLA领域中利用大规模数据预训练再迁移至机器人任务的思路一致。该工作聚焦于数据采集与策略学习的闭环，与RT-2、OpenVLA等工作中利用多模态数据提升机器人操作泛化能力的方向互补。",
  "survey_theme": "操作策略学习",
  "importance_score": 3,
  "keywords": [
    "人形机器人",
    "灵巧操作",
    "遥操作",
    "模仿学习",
    "IMU运动追踪"
  ]
}